setup.py
snipe/__init__.py
snipe/config.py
snipe/snipe.py
snipe.egg-info/PKG-INFO
snipe.egg-info/SOURCES.txt
snipe.egg-info/dependency_links.txt
snipe.egg-info/entry_points.txt
snipe.egg-info/requires.txt
snipe.egg-info/top_level.txt