Metadata-Version: 1.0
Name: snipe
Version: 0.0.5
Summary: Evernote command line tool
Home-page: https://github.com/ngc224/snipe
Author: Yoshihiko Nishida
Author-email: nishida@ngc224.org
License: GPLv3
Keywords: Evernote
Platform: UNKNOWN
